ppcli/__about__.py
ppcli/__init__.py
ppcli/app.py
ppcli-0.0.2.dist-info/METADATA
ppcli-0.0.2.dist-info/WHEEL
ppcli-0.0.2.dist-info/entry_points.txt
ppcli-0.0.2.dist-info/licenses/LICENSE
ppcli-0.0.2.dist-info/RECORD
