Metadata-Version: 2.3
Name: ppcli
Version: 0.0.2
Summary: Dynamic CLI tool to manage project-specific commands using pyproject.toml configuration
Project-URL: Documentation, https://github.com/lykhvar/ppcli#readme
Project-URL: Issues, https://github.com/lykhvar/ppcli/issues
Project-URL: Source, https://github.com/lykhvar/ppcli
Author-email: Artem Lykhvar <me@a10r.com>
License-Expression: MIT
License-File: LICENSE
Keywords: automation,cli,command-line,configuration,dev-tools,developer-tools,project-management,pyproject,scripting,task-runner,tooling,utility
Classifier: Development Status :: 4 - Beta
Classifier: Programming Language :: Python
Classifier: Programming Language :: Python :: 3.8
Classifier: Programming Language :: Python :: 3.9
Classifier: Programming Language :: Python :: 3.10
Classifier: Programming Language :: Python :: 3.11
Classifier: Programming Language :: Python :: 3.12
Requires-Python: >=3.8
Requires-Dist: click>=8.0.6
